oct_tissuemasking/__init__.py
oct_tissuemasking/config.py
oct_tissuemasking/data.py
oct_tissuemasking/losses.py
oct_tissuemasking/main.py
oct_tissuemasking/models.py
oct_tissuemasking/train.py
oct_tissuemasking/utils.py
oct_tissuemasking/checkpoints/__init__.py
oct_tissuemasking/checkpoints/version-1_checkpoint.tar
oct_tissuemasking/checkpoints/__pycache__/__init__.cpython-39.pyc
oct_tissuemasking-0.0.8.dist-info/METADATA
oct_tissuemasking-0.0.8.dist-info/WHEEL
oct_tissuemasking-0.0.8.dist-info/entry_points.txt
oct_tissuemasking-0.0.8.dist-info/top_level.txt
oct_tissuemasking-0.0.8.dist-info/RECORD
