Metadata-Version: 2.1
Name: oct_tissuemasking
Version: 0.0.8
Summary: A PyTorch based package for automated OCT tissue masking.
Home-page: https://github.com/EtienneChollet/oct_tissuemasking
Author: Etienne Chollet
Author-email: etiennepchollet@gmail.com
Classifier: Development Status :: 4 - Beta
Classifier: Intended Audience :: Science/Research
Classifier: Topic :: Software Development :: Build Tools
Classifier: License :: OSI Approved :: MIT License
Classifier: Programming Language :: Python :: 3.9
Requires-Python: ~=3.9
Requires-Dist: torch
Requires-Dist: torchvision
Requires-Dist: torchaudio
Requires-Dist: torchmetrics
Requires-Dist: nibabel
Requires-Dist: matplotlib
Requires-Dist: tensorboard
Requires-Dist: cornucopia
Requires-Dist: cyclopts
